msgcheck/__init__.py
msgcheck/msgcheck.py
msgcheck/po.py
msgcheck/utils.py
msgcheck-4.1.0.dist-info/LICENSE.txt
msgcheck-4.1.0.dist-info/METADATA
msgcheck-4.1.0.dist-info/WHEEL
msgcheck-4.1.0.dist-info/entry_points.txt
msgcheck-4.1.0.dist-info/top_level.txt
msgcheck-4.1.0.dist-info/RECORD
