Metadata-Version: 2.1
Name: msgcheck
Version: 4.1.0
Summary: Gettext file checker.
Home-page: https://github.com/flashcode/msgcheck
Author: Sébastien Helleu
Author-email: flashcode@flashtux.org
License: GPL3
Keywords: gettext
Classifier: Development Status :: 5 - Production/Stable
Classifier: Environment :: Console
Classifier: Intended Audience :: Developers
Classifier: License :: OSI Approved :: GNU General Public License v3 or later (GPLv3+)
Classifier: Natural Language :: English
Classifier: Operating System :: OS Independent
Classifier: Programming Language :: Python
Classifier: Programming Language :: Python :: 3
Classifier: Topic :: Software Development :: Localization
License-File: LICENSE.txt
Requires-Dist: pyenchant
